{
  "id" : "inicioDelProceso",
  "name" : "inicioDelProceso",
  "type" : "form",
  "uuid" : "1c36c1fb-6365-4674-9bd9-79aac892194b",
  "modelVersion" : "2.6",
  "lastUpdate" : 1781532503138,
  "description" : "Page generated with Bonita UI designer",
  "rows" : [
    [
      {
        "type" : "formContainer",
        "dimension" : {
          "xs" : 12
        },
        "propertyValues" : { },
        "reference" : "7ee3c1c3-2f47-4ee8-95d9-f7d904259fb7",
        "hasValidationError" : false,
        "id" : "pbFormContainer",
        "container" : {
          "type" : "container",
          "dimension" : {
            "xs" : 12
          },
          "propertyValues" : { },
          "reference" : "248a7318-3b7f-4e32-aa71-b639dc570891",
          "hasValidationError" : false,
          "id" : "pbContainer",
          "rows" : [
            [
              {
                "type" : "component",
                "dimension" : {
                  "xs" : 12,
                  "sm" : 12,
                  "md" : 12,
                  "lg" : 12
                },
                "propertyValues" : {
                  "cssClasses" : {
                    "type" : "constant",
                    "value" : ""
                  },
                  "hidden" : {
                    "type" : "constant",
                    "value" : false
                  },
                  "allowHTML" : {
                    "type" : "constant",
                    "value" : false
                  },
                  "text" : {
                    "type" : "interpolation",
                    "value" : "Inicio Del Proceso"
                  },
                  "level" : {
                    "type" : "constant",
                    "value" : "Level 2"
                  },
                  "alignment" : {
                    "type" : "constant",
                    "value" : "left"
                  }
                },
                "reference" : "447c8732-4b70-40c2-a6c7-da1473db4035",
                "hasValidationError" : false,
                "id" : "pbTitle"
              }
            ],
            [
              {
                "type" : "component",
                "dimension" : {
                  "md" : 12,
                  "sm" : 12,
                  "xs" : 12,
                  "lg" : 12
                },
                "propertyValues" : {
                  "labelHidden" : {
                    "type" : "constant",
                    "value" : false
                  },
                  "hidden" : {
                    "type" : "constant",
                    "value" : false
                  },
                  "labelPosition" : {
                    "type" : "constant",
                    "value" : "top"
                  },
                  "cssClasses" : {
                    "type" : "constant",
                    "value" : ""
                  },
                  "labelWidth" : {
                    "type" : "constant",
                    "value" : 1
                  },
                  "readOnly" : {
                    "type" : "constant",
                    "value" : false
                  },
                  "label" : {
                    "type" : "interpolation",
                    "value" : "Dni Paciente"
                  },
                  "placeholder" : {
                    "type" : "constant"
                  },
                  "type" : {
                    "type" : "constant",
                    "value" : "text"
                  },
                  "dimension" : {
                    "type" : "constant",
                    "value" : 12
                  },
                  "value" : {
                    "type" : "variable",
                    "value" : "formInput.dniPaciente"
                  },
                  "required" : {
                    "type" : "constant",
                    "value" : true
                  }
                },
                "reference" : "4f361af2-98c5-4f0f-b74a-44061627875f",
                "hasValidationError" : false,
                "id" : "pbInput",
                "description" : ""
              }
            ],
            [
              {
                "type" : "component",
                "dimension" : {
                  "md" : 12,
                  "sm" : 12,
                  "xs" : 12,
                  "lg" : 12
                },
                "propertyValues" : {
                  "labelHidden" : {
                    "type" : "constant",
                    "value" : false
                  },
                  "hidden" : {
                    "type" : "constant",
                    "value" : false
                  },
                  "labelPosition" : {
                    "type" : "constant",
                    "value" : "top"
                  },
                  "cssClasses" : {
                    "type" : "constant",
                    "value" : ""
                  },
                  "labelWidth" : {
                    "type" : "constant",
                    "value" : 1
                  },
                  "readOnly" : {
                    "type" : "constant",
                    "value" : false
                  },
                  "label" : {
                    "type" : "interpolation",
                    "value" : "Numero Orden"
                  },
                  "placeholder" : {
                    "type" : "constant"
                  },
                  "type" : {
                    "type" : "constant",
                    "value" : "text"
                  },
                  "dimension" : {
                    "type" : "constant",
                    "value" : 12
                  },
                  "value" : {
                    "type" : "variable",
                    "value" : "formInput.numeroOrden"
                  },
                  "required" : {
                    "type" : "constant",
                    "value" : true
                  },
                  "allowHTML" : {
                    "type" : "constant",
                    "value" : false
                  },
                  "minLength" : {
                    "type" : "constant",
                    "value" : ""
                  },
                  "maxLength" : {
                    "type" : "constant",
                    "value" : ""
                  },
                  "debounce" : {
                    "type" : "constant",
                    "value" : 0
                  },
                  "min" : {
                    "type" : "constant"
                  },
                  "max" : {
                    "type" : "constant"
                  },
                  "step" : {
                    "type" : "constant",
                    "value" : 1
                  }
                },
                "reference" : "515ae9ea-1b64-4a75-b93a-e466fd186e01",
                "hasValidationError" : false,
                "id" : "pbInput",
                "description" : ""
              }
            ],
            [
              {
                "type" : "component",
                "dimension" : {
                  "md" : 12,
                  "sm" : 12,
                  "xs" : 12,
                  "lg" : 12
                },
                "propertyValues" : {
                  "labelHidden" : {
                    "type" : "constant",
                    "value" : false
                  },
                  "hidden" : {
                    "type" : "constant",
                    "value" : false
                  },
                  "labelPosition" : {
                    "type" : "constant",
                    "value" : "top"
                  },
                  "cssClasses" : {
                    "type" : "constant",
                    "value" : ""
                  },
                  "labelWidth" : {
                    "type" : "constant",
                    "value" : 1
                  },
                  "readOnly" : {
                    "type" : "constant",
                    "value" : false
                  },
                  "label" : {
                    "type" : "interpolation",
                    "value" : "Especialidad"
                  },
                  "placeholder" : {
                    "type" : "constant"
                  },
                  "type" : {
                    "type" : "constant",
                    "value" : "text"
                  },
                  "dimension" : {
                    "type" : "constant",
                    "value" : 12
                  },
                  "value" : {
                    "type" : "variable",
                    "value" : "formInput.especialidad"
                  },
                  "required" : {
                    "type" : "constant",
                    "value" : true
                  }
                },
                "reference" : "ac7778b7-83c8-40a1-bdd1-ec7ee9e22963",
                "hasValidationError" : false,
                "id" : "pbInput",
                "description" : ""
              }
            ],
            [
              {
                "type" : "component",
                "dimension" : {
                  "md" : 12,
                  "sm" : 12,
                  "xs" : 12,
                  "lg" : 12
                },
                "propertyValues" : {
                  "labelHidden" : {
                    "type" : "constant",
                    "value" : false
                  },
                  "hidden" : {
                    "type" : "constant",
                    "value" : false
                  },
                  "labelPosition" : {
                    "type" : "constant",
                    "value" : "top"
                  },
                  "cssClasses" : {
                    "type" : "constant",
                    "value" : ""
                  },
                  "labelWidth" : {
                    "type" : "constant",
                    "value" : 1
                  },
                  "readOnly" : {
                    "type" : "constant",
                    "value" : false
                  },
                  "label" : {
                    "type" : "interpolation",
                    "value" : "Medico Solicitante"
                  },
                  "placeholder" : {
                    "type" : "constant"
                  },
                  "type" : {
                    "type" : "constant",
                    "value" : "text"
                  },
                  "dimension" : {
                    "type" : "constant",
                    "value" : 12
                  },
                  "value" : {
                    "type" : "variable",
                    "value" : "formInput.medicoSolicitante"
                  },
                  "required" : {
                    "type" : "constant",
                    "value" : true
                  }
                },
                "reference" : "20579499-c060-48fe-afe9-5c9177d8e5aa",
                "hasValidationError" : false,
                "id" : "pbInput",
                "description" : ""
              }
            ],
            [
              {
                "type" : "component",
                "dimension" : {
                  "md" : 12,
                  "sm" : 12,
                  "xs" : 12,
                  "lg" : 12
                },
                "propertyValues" : {
                  "removeItem" : {
                    "type" : "variable"
                  },
                  "hidden" : {
                    "type" : "constant",
                    "value" : false
                  },
                  "cssClasses" : {
                    "type" : "constant",
                    "value" : ""
                  },
                  "buttonStyle" : {
                    "type" : "constant",
                    "value" : "primary"
                  },
                  "label" : {
                    "type" : "interpolation",
                    "value" : "Submit"
                  },
                  "dataToSend" : {
                    "type" : "expression",
                    "value" : "formOutput"
                  },
                  "dataFromError" : {
                    "type" : "variable",
                    "value" : "formOutput._submitError"
                  },
                  "allowHTML" : {
                    "type" : "constant",
                    "value" : false
                  },
                  "labelHidden" : {
                    "type" : "constant",
                    "value" : false
                  },
                  "collectionPosition" : {
                    "type" : "constant"
                  },
                  "targetUrlOnSuccess" : {
                    "type" : "interpolation",
                    "value" : "/bonita"
                  },
                  "action" : {
                    "type" : "constant",
                    "value" : "Start process"
                  },
                  "collectionToModify" : {
                    "type" : "variable"
                  },
                  "valueToAdd" : {
                    "type" : "expression"
                  },
                  "disabled" : {
                    "type" : "expression",
                    "value" : "$form.$invalid"
                  },
                  "alignment" : {
                    "type" : "constant",
                    "value" : "center"
                  },
                  "dimension" : {
                    "type" : "constant",
                    "value" : 12
                  }
                },
                "reference" : "0ced71e2-640c-499e-b7f7-6948620224d5",
                "hasValidationError" : false,
                "id" : "pbButton",
                "description" : ""
              }
            ],
            [
              {
                "type" : "component",
                "dimension" : {
                  "md" : 12,
                  "sm" : 12,
                  "xs" : 12,
                  "lg" : 12
                },
                "propertyValues" : {
                  "allowHTML" : {
                    "type" : "constant",
                    "value" : true
                  },
                  "allowHtml" : {
                    "type" : "constant",
                    "value" : true
                  },
                  "labelHidden" : {
                    "type" : "constant",
                    "value" : true
                  },
                  "hidden" : {
                    "type" : "expression",
                    "value" : "!formOutput._submitError.message"
                  },
                  "cssClasses" : {
                    "type" : "constant",
                    "value" : "alert alert-danger col-lg-6 col-lg-offset-3"
                  },
                  "label" : {
                    "type" : "interpolation"
                  },
                  "text" : {
                    "type" : "interpolation",
                    "value" : "<strong>Debug message</strong>\n<br/>\n{{formOutput._submitError.message}}\n{{submit_errors_list}}"
                  },
                  "alignment" : {
                    "type" : "constant",
                    "value" : "left"
                  },
                  "dimension" : {
                    "type" : "constant",
                    "value" : 12
                  }
                },
                "reference" : "d6c926ef-6617-4e68-a92c-66f08e8fd0ed",
                "hasValidationError" : false,
                "id" : "pbText",
                "description" : ""
              }
            ]
          ]
        }
      }
    ]
  ],
  "variables" : {
    "formInput" : {
      "type" : "json",
      "value" : [
        "{\r",
        "  \"dniPaciente\" : \"\",\r",
        "  \"numeroOrden\" : \"\",\r",
        "  \"especialidad\" : \"\",\r",
        "  \"medicoSolicitante\" : \"\"\r",
        "}"
      ],
      "exposed" : false
    },
    "submit_errors_list" : {
      "type" : "expression",
      "value" : [
        "if($data.formOutput && $data.formOutput._submitError && $data.formOutput._submitError.explanations){",
        "\tconst liElements = $data.formOutput._submitError.explanations",
        "\t\t.filter(cause => cause !== null)",
        "\t\t.map(cause => \"<li>\" + cause + \"</li>\")",
        "\t\t.join('');",
        "\tif(liElements){",
        "\t\treturn \"<ul>\" + liElements + \"</ul>\";",
        "\t}",
        "}"
      ],
      "exposed" : false
    },
    "formOutput" : {
      "type" : "expression",
      "value" : [
        "return {",
        "\tdniPaciente: $data.formInput.dniPaciente,",
        "\tnumeroOrden: $data.formInput.numeroOrden,",
        "\tespecialidad: $data.formInput.especialidad,",
        "\tmedicoSolicitante: $data.formInput.medicoSolicitante",
        "}"
      ],
      "exposed" : false
    }
  },
  "assets" : [
    {
      "id" : "52b3871d-a686-46a4-9c42-f500e750baf4",
      "name" : "style.css",
      "type" : "css",
      "order" : 0,
      "external" : false
    },
    {
      "id" : "dfbc794e-9f4d-4ff5-81e0-b386fa6eba35",
      "name" : "localization.json",
      "type" : "json",
      "order" : 0,
      "external" : false
    }
  ],
  "inactiveAssets" : [ ],
  "webResources" : [ ],
  "hasValidationError" : false
}